clockpkg/__init__.py
clockpkg-1.20.21.dist-info/LICENSE.txt
clockpkg-1.20.21.dist-info/METADATA
clockpkg-1.20.21.dist-info/WHEEL
clockpkg-1.20.21.dist-info/top_level.txt
clockpkg-1.20.21.dist-info/RECORD
