Metadata-Version: 2.1
Name: clockpkg
Version: 1.20.21
Summary: Simple package to make an analog clock.
Home-page: https://github.com/Harshdeepsingh0311/clockpkg
Author: Harshdeep Singh
Author-email: harshdeepsinghbakshi2005@gmail.com
License: UNKNOWN
